geobricks_downloader
