Metadata-Version: 1.0
Name: GeobricksDownloader
Version: 0.1.2
Summary: Core functionalities for geospatial data download.
Home-page: http://pypi.python.org/pypi/GeobricksDownloader/
Author: Simone Murzilli; Guido Barbaglia
Author-email: geobrickspy@gmail.com
License: LICENSE.txt
Platform: UNKNOWN
